{
    "haskellNix": {
        "branch": "master",
        "description": "Alternative Haskell Infrastructure for Nixpkgs",
        "homepage": "https://input-output-hk.github.io/haskell.nix",
        "owner": "input-output-hk",
        "repo": "haskell.nix",
        "rev": "4de59adf61464a76c63a1a2883e9cdc00931fa57",
        "sha256": "0d0lz09hnp2ixavxzmwig08s0v1261156g751y3havv81pr49p8k",
        "type": "tarball",
        "url": "https://github.com/input-output-hk/haskell.nix/archive/4de59adf61464a76c63a1a2883e9cdc00931fa57.tar.gz",
        "url_template": "https://github.com/<owner>/<repo>/archive/<rev>.tar.gz"
    },
    "niv": {
        "branch": "master",
        "description": "Easy dependency management for Nix projects",
        "homepage": "https://github.com/nmattia/niv",
        "owner": "nmattia",
        "repo": "niv",
        "rev": "dd678782cae74508d6b4824580d2b0935308011e",
        "sha256": "0dk8dhh9vla2s409anmrfkva6h3r32xmz3cm8ha09wyk8iyf1f87",
        "type": "tarball",
        "url": "https://github.com/nmattia/niv/archive/dd678782cae74508d6b4824580d2b0935308011e.tar.gz",
        "url_template": "https://github.com/<owner>/<repo>/archive/<rev>.tar.gz"
    },
    "nixpkgs": {
        "branch": "nixos-unstable",
        "description": "Nix Packages collection",
        "homepage": "",
        "owner": "NixOS",
        "repo": "nixpkgs",
        "rev": "e4bae1bd10c9c57b2cf517953ab70060a828ee6f",
        "sha256": "09qwbfkvk3jmqlpgis4v1m1fmh7zffi8drybb03mjqa95bynbs99",
        "type": "tarball",
        "url": "https://github.com/NixOS/nixpkgs/archive/e4bae1bd10c9c57b2cf517953ab70060a828ee6f.tar.gz",
        "url_template": "https://github.com/<owner>/<repo>/archive/<rev>.tar.gz"
    }
}
